LICENSE
MANIFEST.in
README.md
setup.py
dict_utils/__init__.py
dict_utils/dict_utils.py
dict_utils.egg-info/PKG-INFO
dict_utils.egg-info/SOURCES.txt
dict_utils.egg-info/dependency_links.txt
dict_utils.egg-info/not-zip-safe
dict_utils.egg-info/top_level.txt