Metadata-Version: 1.0
Name: dict-utils
Version: 0.1.2
Summary: Set of utilities and accessory methods to work with Python dicts.
Home-page: https://github.com/glowdigitalmedia/dict-utils/
Author: Andrea Grandi
Author-email: a.grandi@gmail.com
License: UNKNOWN
Platform: any
